latex2edx/__init__.py
latex2edx/abox.py
latex2edx/course_tests.py
latex2edx/latex2edx.css
latex2edx/latex2edx.js
latex2edx/main.py
latex2edx/plastexit.py
latex2edx/xbundle.py
latex2edx/plastexpy/__init__.py
latex2edx/plastexpy/edXpsl.py
latex2edx/python_lib/general_hint_system.py
latex2edx/python_lib/ghs_tests.py
latex2edx/python_lib/test_ghs.py
latex2edx/render/Math.zpts
latex2edx/render/edXpsl.zpts
latex2edx/test/__init__.py
latex2edx/test/test_abox.py
latex2edx/test/test_allowdirs.py
latex2edx/test/test_bad_abox.py
latex2edx/test/test_bad_script.py
latex2edx/test/test_course_unit_tests.py
latex2edx/test/test_custom_html.py
latex2edx/test/test_dndtex.py
latex2edx/test/test_edxaskta.py
latex2edx/test/test_edxmath.py
latex2edx/test/test_edxtext.py
latex2edx/test/test_edxxml.py
latex2edx/test/test_examples.py
latex2edx/test/test_ghs_unittest.py
latex2edx/test/test_hints.py
latex2edx/test/test_image.py
latex2edx/test/test_include.py
latex2edx/test/test_keyword.py
latex2edx/test/test_marginote.py
latex2edx/test/test_math.py
latex2edx/test/test_min2.py
latex2edx/test/test_output_fmts.py
latex2edx/test/test_policy.py
latex2edx/test/test_showhide.py
latex2edx/test/test_timestamp.py
latex2edx/test/test_toc.py
latex2edx/test/test_video.py
latex2edx/test/test_xbundle.py
latex2edx/test/util.py
latex2edx/testtex/example-html-text.tex
latex2edx/testtex/example-image.png
latex2edx/testtex/example1.tex
latex2edx/testtex/example10_badpolicy.tex
latex2edx/testtex/example11_toc_test.tex
latex2edx/testtex/example12_index.tex
latex2edx/testtex/example13_edxxml.tex
latex2edx/testtex/example14_showhide.tex
latex2edx/testtex/example15_directories.tex
latex2edx/testtex/example17_toc_vert.tex
latex2edx/testtex/example1_bad_script.tex
latex2edx/testtex/example2.tex
latex2edx/testtex/example3.tex
latex2edx/testtex/example4.tex
latex2edx/testtex/example5.tex
latex2edx/testtex/example5a.tex
latex2edx/testtex/example6.tex
latex2edx/testtex/example7.tex
latex2edx/testtex/example7_bad.tex
latex2edx-1.6.2.dist-info/AUTHORS
latex2edx-1.6.2.dist-info/LICENSE.txt
latex2edx-1.6.2.dist-info/METADATA
latex2edx-1.6.2.dist-info/WHEEL
latex2edx-1.6.2.dist-info/entry_points.txt
latex2edx-1.6.2.dist-info/top_level.txt
latex2edx-1.6.2.dist-info/RECORD
