Metadata-Version: 2.1
Name: latex2edx
Version: 1.6.2
Summary: Converter from latex to edX XML format course content files
Home-page: http://pypi.python.org/pypi/latex2edx/
Author: I. Chuang
Author-email: ichuang@mit.edu
License: LICENSE.txt
Platform: UNKNOWN
Requires-Dist: lxml
Requires-Dist: path.py
Requires-Dist: plastex
Requires-Dist: beautifulsoup4
Requires-Dist: latex2dnd
Requires-Dist: pyyaml
